binaryandserializablemath/__init__.py
binaryandserializablemath/main.py
BinaryAndSerializableMath-1.0.1.dist-info/METADATA
BinaryAndSerializableMath-1.0.1.dist-info/WHEEL
BinaryAndSerializableMath-1.0.1.dist-info/top_level.txt
BinaryAndSerializableMath-1.0.1.dist-info/RECORD
