Metadata-Version: 2.1
Name: BinaryAndSerializableMath
Version: 1.0.1
